crypto_memory_mcp/__init__.py
crypto_memory_mcp/__main__.py
crypto_memory_mcp/server.py
crypto_memory_mcp-1.0.4.dist-info/licenses/LICENSE
crypto_memory_mcp-1.0.4.dist-info/METADATA
crypto_memory_mcp-1.0.4.dist-info/WHEEL
crypto_memory_mcp-1.0.4.dist-info/entry_points.txt
crypto_memory_mcp-1.0.4.dist-info/top_level.txt
crypto_memory_mcp-1.0.4.dist-info/RECORD
