Metadata-Version: 2.4
Name: crypto-memory-mcp
Version: 1.0.4
Summary: A Memory-Enhanced MCP Server for Cryptocurrency Analysis using mem0
Home-page: https://github.com/crypto-memory-mcp
Author: Crypto Memory MCP
Author-email: Crypto Memory MCP <crypto@example.com>
License: MIT
Project-URL: Homepage, https://github.com/crypto-memory-mcp
Project-URL: Repository, https://github.com/crypto-memory-mcp.git
Requires-Python: >=3.8
License-File: LICENSE
Requires-Dist: mcp>=1.0.0
Requires-Dist: mem0ai>=0.1.0
Requires-Dist: pydantic>=2.0.0
Requires-Dist: aiohttp>=3.8.0
Requires-Dist: python-dotenv>=1.0.0
Dynamic: author
Dynamic: home-page
Dynamic: license-file
Dynamic: requires-python
